setup.py
on_http_api1_1/__init__.py
on_http_api1_1/api_client.py
on_http_api1_1/configuration.py
on_http_api1_1/rest.py
on_http_api1_1.egg-info/PKG-INFO
on_http_api1_1.egg-info/SOURCES.txt
on_http_api1_1.egg-info/dependency_links.txt
on_http_api1_1.egg-info/requires.txt
on_http_api1_1.egg-info/top_level.txt
on_http_api1_1/apis/__init__.py
on_http_api1_1/apis/catalog_api.py
on_http_api1_1/apis/catalogs_api.py
on_http_api1_1/apis/config_api.py
on_http_api1_1/apis/delete_api.py
on_http_api1_1/apis/dhcp_api.py
on_http_api1_1/apis/files_api.py
on_http_api1_1/apis/get_api.py
on_http_api1_1/apis/identify_api.py
on_http_api1_1/apis/lookups_api.py
on_http_api1_1/apis/nodes_api.py
on_http_api1_1/apis/obm_api.py
on_http_api1_1/apis/obms_api.py
on_http_api1_1/apis/patch_api.py
on_http_api1_1/apis/pollers_api.py
on_http_api1_1/apis/post_api.py
on_http_api1_1/apis/profiles_api.py
on_http_api1_1/apis/put_api.py
on_http_api1_1/apis/skus_api.py
on_http_api1_1/apis/tags_api.py
on_http_api1_1/apis/task_api.py
on_http_api1_1/apis/templates_api.py
on_http_api1_1/apis/versions_api.py
on_http_api1_1/apis/whitelist_api.py
on_http_api1_1/apis/workflow_api.py
on_http_api1_1/models/__init__.py
on_http_api1_1/models/body.py
on_http_api1_1/models/body_1.py
on_http_api1_1/models/body_10.py
on_http_api1_1/models/body_2.py
on_http_api1_1/models/body_3.py
on_http_api1_1/models/body_4.py
on_http_api1_1/models/body_5.py
on_http_api1_1/models/body_6.py
on_http_api1_1/models/body_7.py
on_http_api1_1/models/body_8.py
on_http_api1_1/models/body_9.py
on_http_api1_1/models/catalog.py
on_http_api1_1/models/content.py
on_http_api1_1/models/content_1.py
on_http_api1_1/models/error.py
on_http_api1_1/models/graphobject.py
on_http_api1_1/models/identifiers.py
on_http_api1_1/models/inline_response_200.py
on_http_api1_1/models/lease.py
on_http_api1_1/models/node.py
on_http_api1_1/models/sku.py
on_http_api1_1/models/tag.py