Metadata-Version: 1.0
Name: on-http-api1-1
Version: 1.0.2
Summary: Monorail API
Home-page: UNKNOWN
Author: UNKNOWN
Author-email: UNKNOWN
License: UNKNOWN
Keywords: Swagger,Monorail API
Platform: UNKNOWN
